ibisclient/__init__.py
ibisclient/connection.py
ibisclient/dto.py
ibisclient/methods.py
ibisclient-1.3.2.dist-info/METADATA
ibisclient-1.3.2.dist-info/WHEEL
ibisclient-1.3.2.dist-info/top_level.txt
ibisclient-1.3.2.dist-info/RECORD
