Metadata-Version: 2.1
Name: ibisclient
Version: 1.3.2
Summary: Lookup API client
Home-page: https://www.lookup.cam.ac.uk/doc/ws-doc/
License: LGPL
Platform: UNKNOWN
Requires-Dist: requests (~=2.26)
